enumecg/__init__.py
enumecg/__main__.py
enumecg/cli.py
enumecg/definitions.py
enumecg/exceptions.py
enumecg/generators.py
enumecg/utils.py
enumecg/templates/enum_definitions.hh.in
enumecg/templates/doxygen/associate_namespace.doc.in
enumecg/templates/doxygen/enhance.doc.in
enumecg/templates/doxygen/enhanced_enum.doc.in
enumecg/templates/doxygen/enum.doc.in
enumecg/templates/doxygen/enumerator_constant.doc.in
enumecg/templates/doxygen/function_alias.doc.in
enumecg/templates/doxygen/internal_begin.doc.in
enumecg/templates/doxygen/internal_end.doc.in
enumecg/templates/doxygen/label_enum.doc.in
enumecg/templates/doxygen/value_constant.doc.in
EnumECG-0.8.dist-info/entry_points.txt
EnumECG-0.8.dist-info/LICENSE
EnumECG-0.8.dist-info/WHEEL
EnumECG-0.8.dist-info/METADATA
EnumECG-0.8.dist-info/RECORD
